energy_tariff_scheduler/__init__.py
energy_tariff_scheduler/config.py
energy_tariff_scheduler/prices.py
energy_tariff_scheduler/runner.py
energy_tariff_scheduler/schedules.py
energy_tariff_scheduler-0.0.8.dist-info/LICENSE
energy_tariff_scheduler-0.0.8.dist-info/METADATA
energy_tariff_scheduler-0.0.8.dist-info/WHEEL
energy_tariff_scheduler-0.0.8.dist-info/top_level.txt
energy_tariff_scheduler-0.0.8.dist-info/RECORD
