Metadata-Version: 2.2
Name: energy_tariff_scheduler
Version: 0.0.8
Summary: Schedule actions based on energy tariffs
Home-page: https://github.com/craigwh10/energy-tariff-scheduler
Author: Craig White
Author-email: dev.craigw@gmail.com
License: MIT
Classifier: Programming Language :: Python :: 3
Classifier: License :: OSI Approved :: MIT License
Classifier: Operating System :: OS Independent
Requires-Python: >=3.10
License-File: LICENSE
Requires-Dist: pydantic==2.10.4
Requires-Dist: requests==2.32.3
Requires-Dist: python-dateutil==2.9.0.post0
Requires-Dist: apscheduler==3.11.0
Requires-Dist: tenacity==9.0.0
Dynamic: author
Dynamic: author-email
Dynamic: classifier
Dynamic: description
Dynamic: description-content-type
Dynamic: home-page
Dynamic: license
Dynamic: requires-dist
Dynamic: requires-python
Dynamic: summary
